[
  {
    "targets": [
      "backend:8000"
    ],
    "labels": {
      "job": "infrascope-backend",
      "service_name": "backend",
      "__metrics_path__": "/metrics"
    }
  },
  {
    "targets": [
      "discovery-service:8012"
    ],
    "labels": {
      "job": "infrascope-discovery-service",
      "service_name": "discovery-service",
      "__metrics_path__": "/metrics"
    }
  },
  {
    "targets": [
      "ml-service:8010"
    ],
    "labels": {
      "job": "infrascope-ml-service",
      "service_name": "ml-service",
      "__metrics_path__": "/metrics"
    }
  },
  {
    "targets": [
      "network-control-service:8013"
    ],
    "labels": {
      "job": "infrascope-network-control-service",
      "service_name": "network-control-service",
      "__metrics_path__": "/metrics"
    }
  },
  {
    "targets": [
      "polling-service:8011"
    ],
    "labels": {
      "job": "infrascope-polling-service",
      "service_name": "polling-service",
      "__metrics_path__": "/metrics"
    }
  },
  {
    "targets": [
      "worker:9108"
    ],
    "labels": {
      "job": "infrascope-worker",
      "service_name": "worker",
      "__metrics_path__": "/"
    }
  }
]